{
	"goods_1":[{"bigImg":"20160816150003_394780.jpg"},
			{"middleImg":[{"img":"12650_0.jpg!150.jpg","discount":"2019.00","original":"3600"},
							{"img":"571_0.jpg!150.jpg","discount":"0.00","original":"38"},
							{"img":"12650_0.jpg!150.jpg","discount":"92.00","original":"259"},
							{"img":"571_0.jpg!150.jpg","discount":"69.00","original":"143.00"},
							{"img":"12650_0.jpg!150.jpg","discount":"16.00","original":"29"},
							{"img":"571_0.jpg!150.jpg","discount":"23.00","original":"49"}]},
			{"littleImg":[{"img":"20160330173505_157737.jpg","brand":"挪威小鱼"},
						{"img":"20150204115153.jpg","brand":"乐高"},
						{"img":"20160330173505_157737.jpg","brand":"健安喜"},
						{"img":"20150204115153.jpg","brand":"Let's DHA"},
						{"img":"20160330173505_157737.jpg","brand":"普丽普莱"},
						{"img":"20150204115153.jpg","brand":"Schiff"},
						{"img":"20160330173505_157737.jpg","brand":"MK"},
						{"img":"20150204115153.jpg","brand":"coach"},
						{"img":"20160330173505_157737.jpg","brand":"箭牌"},
						{"img":"20150204115153.jpg","brand":"加州宝宝"}]}
				]
}
